setup.cfg
setup.py
maybe/__init__.py
maybe/maybe.py
maybe/syscall_filters.py
maybe/utilities.py
maybe.egg-info/PKG-INFO
maybe.egg-info/SOURCES.txt
maybe.egg-info/dependency_links.txt
maybe.egg-info/entry_points.txt
maybe.egg-info/requires.txt
maybe.egg-info/top_level.txt